azure/healthinsights/cancerprofiling/__init__.py
azure/healthinsights/cancerprofiling/_client.py
azure/healthinsights/cancerprofiling/_configuration.py
azure/healthinsights/cancerprofiling/_model_base.py
azure/healthinsights/cancerprofiling/_patch.py
azure/healthinsights/cancerprofiling/_serialization.py
azure/healthinsights/cancerprofiling/_vendor.py
azure/healthinsights/cancerprofiling/_version.py
azure/healthinsights/cancerprofiling/py.typed
azure/healthinsights/cancerprofiling/_operations/__init__.py
azure/healthinsights/cancerprofiling/_operations/_operations.py
azure/healthinsights/cancerprofiling/_operations/_patch.py
azure/healthinsights/cancerprofiling/aio/__init__.py
azure/healthinsights/cancerprofiling/aio/_client.py
azure/healthinsights/cancerprofiling/aio/_configuration.py
azure/healthinsights/cancerprofiling/aio/_patch.py
azure/healthinsights/cancerprofiling/aio/_vendor.py
azure/healthinsights/cancerprofiling/aio/_operations/__init__.py
azure/healthinsights/cancerprofiling/aio/_operations/_operations.py
azure/healthinsights/cancerprofiling/aio/_operations/_patch.py
azure/healthinsights/cancerprofiling/models/__init__.py
azure/healthinsights/cancerprofiling/models/_enums.py
azure/healthinsights/cancerprofiling/models/_models.py
azure/healthinsights/cancerprofiling/models/_patch.py
azure_healthinsights_cancerprofiling-1.0.0b1.post1.dist-info/LICENSE
azure_healthinsights_cancerprofiling-1.0.0b1.post1.dist-info/METADATA
azure_healthinsights_cancerprofiling-1.0.0b1.post1.dist-info/WHEEL
azure_healthinsights_cancerprofiling-1.0.0b1.post1.dist-info/top_level.txt
azure_healthinsights_cancerprofiling-1.0.0b1.post1.dist-info/RECORD
